simple_xlsx_writer/__init__.py
simple_xlsx_writer/common.py
simple_xlsx_writer/oracle_handler.py
simple_xlsx_writer/postgresql_handler.py
simple_xlsx_writer/writer.py
simple_xlsx_writer-0.3.2.dist-info/METADATA
simple_xlsx_writer-0.3.2.dist-info/WHEEL
simple_xlsx_writer-0.3.2.dist-info/licenses/LICENSE
simple_xlsx_writer-0.3.2.dist-info/RECORD
