Metadata-Version: 2.4
Name: simple-xlsx-writer
Version: 0.3.2
Summary: Save large amounts of data to small xlsx files
Project-URL: Homepage, https://github.com/krzys9876/simple_xlsx_writer
Project-URL: Repository, https://github.com/krzys9876/simple_xlsx_writer
Author-email: Krzysztof Ruta <krzys9876@gmail.com>
Maintainer-email: Krzysztof Ruta <krzys9876@gmail.com>
License: MIT License
License-File: LICENSE
Keywords: Excel,database,export,python,xlsx
Classifier: Development Status :: 4 - Beta
Classifier: Programming Language :: Python
Requires-Python: >=3.11
Provides-Extra: oracle
Requires-Dist: oracledb; extra == 'oracle'
Provides-Extra: postgresql
Requires-Dist: psycopg[binary]; extra == 'postgresql'
